citus_dump/__init__.py
citus_dump/__main__.py
citus_dump/classes.py
citus_dump/configuration.py
citus_dump/coordinator_utils.py
citus_dump/dump_utils.py
citus_dump/exceptions.py
citus_dump/formation_utils.py
citus_dump/node_utils.py
citus_dump/restore_utils.py
citus_dump/utils.py
citus_dump/commands/__init__.py
citus_dump/commands/citus_copy_load.py
citus_dump/commands/citus_dump.py
citus_dump/commands/citus_loader.py
citus_dump/commands/citus_reinit_restore.py
citus_dump/commands/citus_restore.py
py_citus_loader-2.1.0.dist-info/LICENSE
py_citus_loader-2.1.0.dist-info/METADATA
py_citus_loader-2.1.0.dist-info/WHEEL
py_citus_loader-2.1.0.dist-info/entry_points.txt
py_citus_loader-2.1.0.dist-info/top_level.txt
py_citus_loader-2.1.0.dist-info/RECORD
