Metadata-Version: 2.1
Name: py-citus-loader
Version: 2.1.0
Summary: A python command line tool to provide the commands necessary to run on citus to have a balanced cluster
Home-page: https://github.com/citusdata/python-citus-loader
Author: Louise Grandjonc
Author-email: louise.grandjonc@microsoft.com
License: UNKNOWN
Keywords: postgresql citus dump restore
Platform: UNKNOWN
Classifier: Development Status :: 4 - Beta
Classifier: Topic :: Database
Classifier: License :: OSI Approved :: MIT License
Classifier: Intended Audience :: Developers
Requires-Python: >=3.5
Requires-Dist: psycopg2
Requires-Dist: click
Requires-Dist: pyyaml
